<TextObjectProperties>
  <Layout>
    <Frame>
      <BorderWidth>0</BorderWidth>
      <BorderEffect>FLAT</BorderEffect>
      <Color>
        <Mode>COLORAREA_SOLID</Mode>
        <Luminosity>85</Luminosity>
        <FillDirection>COLORAREA_HORZ</FillDirection>
        <FillPattern>COLORAREA_PATTERN1</FillPattern>
        <PrimaryCol>
          <Col>
            <Red>4</Red>
            <Green>108</Green>
            <Blue>193</Blue>
            <Alpha>255</Alpha>
          </Col>
          <IsCalculated>false</IsCalculated>
          <ColorExpr></ColorExpr>
        </PrimaryCol>
        <SecondaryCol></SecondaryCol>
        <Alpha>255</Alpha>
      </Color>
      <Font></Font>
      <CaptionFont>
        <FontName>Tahoma</FontName>
        <PointSize1000>10000</PointSize1000>
        <Underline>false</Underline>
        <Bold>true</Bold>
        <Italic>false</Italic>
        <DropShadow>false</DropShadow>
      </CaptionFont>
      <Name></Name>
      <Detached>false</Detached>
      <AllowMinimize>false</AllowMinimize>
      <AutoMinimize>false</AutoMinimize>
      <AllowMaximize>false</AllowMaximize>
      <AllowInfo>false</AllowInfo>
      <PrintIcon>false</PrintIcon>
      <CopyIcon>false</CopyIcon>
      <XLIcon>false</XLIcon>
      <SearchIcon>false</SearchIcon>
      <SelectPossibleIcon>false</SelectPossibleIcon>
      <SelectExcludedIcon>false</SelectExcludedIcon>
      <SelectAllIcon>false</SelectAllIcon>
      <ClearIcon>false</ClearIcon>
      <ClearOtherIcon>false</ClearOtherIcon>
      <LockIcon>false</LockIcon>
      <HelpText></HelpText>
      <ObjectId></ObjectId>
      <ShrinkFrameToData>true</ShrinkFrameToData>
      <ShowCaption>false</ShowCaption>
      <MultiLine>0</MultiLine>
      <ActiveBgColor>
        <Mode>COLORAREA_SOLID</Mode>
        <Luminosity>85</Luminosity>
        <FillDirection>COLORAREA_HORZ</FillDirection>
        <FillPattern>COLORAREA_PATTERN1</FillPattern>
        <PrimaryCol>
          <Col>
            <Red>210</Red>
            <Green>210</Green>
            <Blue>210</Blue>
            <Alpha>255</Alpha>
          </Col>
          <IsCalculated>false</IsCalculated>
          <ColorExpr></ColorExpr>
        </PrimaryCol>
        <SecondaryCol>
          <Col>
            <Red>153</Red>
            <Green>153</Green>
            <Blue>153</Blue>
            <Alpha>255</Alpha>
          </Col>
          <IsCalculated>false</IsCalculated>
          <ColorExpr></ColorExpr>
        </SecondaryCol>
        <Alpha>255</Alpha>
      </ActiveBgColor>
      <BgColor>
        <Mode>COLORAREA_SOLID</Mode>
        <Luminosity>85</Luminosity>
        <FillDirection>COLORAREA_HORZ</FillDirection>
        <FillPattern>COLORAREA_PATTERN1</FillPattern>
        <PrimaryCol>
          <Col>
            <Red>232</Red>
            <Green>232</Green>
            <Blue>232</Blue>
            <Alpha>255</Alpha>
          </Col>
          <IsCalculated>false</IsCalculated>
          <ColorExpr></ColorExpr>
        </PrimaryCol>
        <SecondaryCol>
          <Col>
            <Red>200</Red>
            <Green>200</Green>
            <Blue>200</Blue>
            <Alpha>255</Alpha>
          </Col>
          <IsCalculated>false</IsCalculated>
          <ColorExpr></ColorExpr>
        </SecondaryCol>
        <Alpha>255</Alpha>
      </BgColor>
      <ActiveFgColor>
        <Mode>COLORAREA_SOLID</Mode>
        <Luminosity>85</Luminosity>
        <FillDirection>COLORAREA_HORZ</FillDirection>
        <FillPattern>COLORAREA_PATTERN1</FillPattern>
        <PrimaryCol>
          <Col>
            <Red>54</Red>
            <Green>54</Green>
            <Blue>54</Blue>
            <Alpha>255</Alpha>
          </Col>
          <IsCalculated>false</IsCalculated>
          <ColorExpr></ColorExpr>
        </PrimaryCol>
        <SecondaryCol></SecondaryCol>
        <Alpha>255</Alpha>
      </ActiveFgColor>
      <FgColor>
        <Mode>COLORAREA_SOLID</Mode>
        <Luminosity>85</Luminosity>
        <FillDirection>COLORAREA_HORZ</FillDirection>
        <FillPattern>COLORAREA_PATTERN1</FillPattern>
        <PrimaryCol>
          <Col>
            <Red>54</Red>
            <Green>54</Green>
            <Blue>54</Blue>
            <Alpha>255</Alpha>
          </Col>
          <IsCalculated>false</IsCalculated>
          <ColorExpr></ColorExpr>
        </PrimaryCol>
        <SecondaryCol></SecondaryCol>
        <Alpha>255</Alpha>
      </FgColor>
      <FixCorner>true</FixCorner>
      <FixCornerSize>21</FixCornerSize>
      <RelCornerSize>4059000000000000</RelCornerSize>
      <Power>4000000000000000</Power>
      <RoundedShape>true</RoundedShape>
      <EnableTopLeftRounded>true</EnableTopLeftRounded>
      <EnableTopRightRounded>true</EnableTopRightRounded>
      <EnableBottomLeftRounded>true</EnableBottomLeftRounded>
      <EnableBottomRightRounded>true</EnableBottomRightRounded>
      <Light>3FEE666666666666</Light>
      <Dark>3FC3333333333333</Dark>
      <Rainbow>false</Rainbow>
      <TextAdjustHorizontal>0</TextAdjustHorizontal>
      <TextAdjustVertical>4</TextAdjustVertical>
      <Show></Show>
      <AllowMoveSize>true</AllowMoveSize>
      <AllowCopyClone>true</AllowCopyClone>
      <dummy></dummy>
      <CustomObjectGuid enctype="base64"></CustomObjectGuid>
      <CustomObjectProperties enctype="base64"></CustomObjectProperties>
      <ScrollBkgColor>
        <Col>
          <Red>255</Red>
          <Green>255</Green>
          <Blue>255</Blue>
          <Alpha>255</Alpha>
        </Col>
        <IsCalculated>false</IsCalculated>
        <ColorExpr></ColorExpr>
      </ScrollBkgColor>
      <ScrollButtonColor>
        <Col>
          <Red>192</Red>
          <Green>192</Green>
          <Blue>192</Blue>
          <Alpha>255</Alpha>
        </Col>
        <IsCalculated>false</IsCalculated>
        <ColorExpr></ColorExpr>
      </ScrollButtonColor>
      <ScrollStyle>SCROLL_SIX</ScrollStyle>
      <ScrollWidth>38</ScrollWidth>
      <AllowModify>true</AllowModify>
      <CopyImageIcon>false</CopyImageIcon>
      <PreserveScrollPosition>false</PreserveScrollPosition>
      <ShadowIntensity>SHADOW_NONE</ShadowIntensity>
      <OnActivateActionItems></OnActivateActionItems>
      <OnDeactivateActionItems></OnDeactivateActionItems>
      <Extension></Extension>
      <Background></Background>
      <MenuIcon>false</MenuIcon>
      <ExtendedProperties></ExtendedProperties>
      <ExtendedValues></ExtendedValues>
      <StateName></StateName>
    </Frame>
    <LegacyHelpModeThatHasNoEffectWhatSoEver>false</LegacyHelpModeThatHasNoEffectWhatSoEver>
    <TextAdjustHorizontal>1</TextAdjustHorizontal>
    <TextAdjustVertical>4</TextAdjustVertical>
    <TopMargin>10</TopMargin>
    <BottomMargin>10</BottomMargin>
    <LeftMargin>10</LeftMargin>
    <RightMargin>10</RightMargin>
    <TextColor>
      <Mode>COLORAREA_SOLID</Mode>
      <Luminosity>85</Luminosity>
      <FillDirection>COLORAREA_HORZ</FillDirection>
      <FillPattern>COLORAREA_PATTERN1</FillPattern>
      <PrimaryCol>
        <Col>
          <Red>54</Red>
          <Green>54</Green>
          <Blue>54</Blue>
          <Alpha>255</Alpha>
        </Col>
        <IsCalculated>false</IsCalculated>
        <ColorExpr></ColorExpr>
      </PrimaryCol>
      <SecondaryCol></SecondaryCol>
      <Alpha>255</Alpha>
    </TextColor>
    <BkgColor>
      <Mode>COLORAREA_SOLID</Mode>
      <Luminosity>85</Luminosity>
      <FillDirection>COLORAREA_HORZ</FillDirection>
      <FillPattern>COLORAREA_PATTERN1</FillPattern>
      <PrimaryCol>
        <Col>
          <Red>214</Red>
          <Green>231</Green>
          <Blue>248</Blue>
          <Alpha>255</Alpha>
        </Col>
        <IsCalculated>false</IsCalculated>
        <ColorExpr></ColorExpr>
      </PrimaryCol>
      <SecondaryCol></SecondaryCol>
      <Alpha>255</Alpha>
    </BkgColor>
    <BkgImageSettings></BkgImageSettings>
    <BkgMode>BKG_IMAGE</BkgMode>
    <Bmp enctype="base64">
        iVBORw0KGgoAAAANSUhEUgAAAXwAAADsCAIAAAD4lIpqAAAAAXNSR0IArs4c6QAAAARnQU1BAACx
        jwv8YQUAAAAJcEhZcwAADsMAAA7DAcdvqGQAAD0kSURBVHhe7Z13XBRX18ffN08ioKAidhSxIqKo
        sXdjSezdqBFbLMSexLwWLBCRWBJbTCyJRgURwYI1othQiooNCyqCVOm9SsrzvL9wJ5tlZ3d2dnd2
        8hjO9w8+7O7MvXNn7/nOObOzs//zH4IgCBkh6RAEISskHYIgZIWkQxCErJB0CIKQFZIOQRCyQtIh
        CEJWSDoEQcgKSYcgCFkh6RAEISskHYIgZIWkQxCErJB0CIKQFZIOQRCyQtIhCEJWSDoEQcgKSYcg
        CFkh6RAEISskHYIgZIWkQxCErJB0CIKQFZIOQRCyQtIhCEJWSDoEQcgKSYcgCFkh6RAEISskHYIg
        ZIWkQxCErJB0CIKQFZIOQRCyQtIhCEJWSDoEQcgKSYcgCFkh6RAEISskHYIgZIWkQxCErJB0CIKQ
        FZIOQRCyQtIhCEJWSDrEX/z73/8uLS3Nysr67bff8D/3LEFICkmH+MM1v/76661bt9asWTN69OiB
        AwcOGzbs8OHD6enpZB9Cckg6FR045fnz5wsXLmzXrl3NmjX/9a9//U8ZjRs37tGjx/Xr13///Xfy
        DiEhJJ0KDWxy5MiRvn37VqtWDbp56623mHHA//7v/+JhmzZtQkJCkAdxKxCEwZB0Ki4wTkRExKhR
        o0xMTKAYTjblgYmQAeXn51OyQ0gFSafiUlJSsnLlSgsLC+UERwXICEkQsiE6uUNIBUmn4pKamjpz
        5sx33nlHU5rDQLKD+uuXX375/fffuTUJwgBIOhWX2NjYyZMnv/3228LSAU2aNElOTkayw61JEAZA
        0nkDQF3Dh3vNACIjI8eMGSNGOtbW1levXjX26WRuYH/CPUv84yDp/LeDoqaoqCgzMzMlJQUFEf7J
        y8srLS01PCwfPHgwbNgwVE9apVO9enV3d/fXr19za0oNxojG8/Pzc3JysrOz8Q+qOfLOPxWSzn8v
        iDqEYkRExIoVKxwcHOrWrWtjY9OuXbuZM2eeOXMmIyMDqYchkRkcHPzee++JkQ4WaNmyZUxMjOQi
        QIMFBQV3797dtWvX1KlT+/fv36dPnwULFly6dAmSZW41sFOsjnYg7uLiYuwxCA7QefG/EZLOfy8I
        lVOnTpmYmMAL4K0/wf+mpqZOTk5IVWAl/YIHgbd7926ITKtxGPXq1fP09JQ8VtPS0jZt2tS0aVNU
        eWyYCsaNG3f+/HlkPdhUbmndwdYmJSWdPXt27969hw4dCgsLe/z4cWxsLFIqQ5olDIGkowOYwQCB
        h4MzJi6mb0JCAg6hmL54nltIItBgeHg46hqEHxf3SsAUsM+IESNCQkJKSkr06J19Xo5Q51rURv36
        9Q8fPiytdFBJrV692tLSEmPkuw/PYPOOHDmCUotbQUewIizDLkR655130BpkjYEgv9u6dSveO2O8
        cYRWSDpiwezMzc199OhRYGDgnj17cBx2dHScMmXKwYMHnz17pl/kC4C+UGuojUYG887IkSPhJj1O
        8SIg16xZo9ZoamnUqNHly5cljFL469ixY23atBE4k43nO3ToUFhYqEenWAWJkoWFBXRTliC+hdYA
        +x+mQxEH72AzuBUIuSDpiAJR/eLFi82bN/ft2xfzFfOY6QB/ETPjx49HQCLlkSogEdv79++vVKkS
        uuDiTx0shD7//PNXr17p0fW3336LsQh3oaBFixZRUVHoRaoxIluE9ZCDYAhcH+rAq8nJybp2iuUj
        IyNtbW3x7mhqHymPu7t7ZmYm5TsyQ9LRDiZldHT0rFmz2AxGlDIwcdk/eLJnz55XrlyRKt9JT093
        cHBAdyw8hGncuDEO6XokO9euXevVq5dAMqUAkn3//fehCQmDMzU1dfHixSwN4bpRB15FJatrv6Wl
        pXi/zM3NBRrHqJFnIdui6x5lhqSjBUz3rKwsDw8P4SoADBs2DHWWHsHPByUb0hzhaFQAa+zbt6+4
        uFjXyExLS3Nzc8MBX9O4FNSsWRMVpd7nVtQCj0+dOlUgE2HgVZZhcauJA403adIERhMeGl51dnZm
        d/Dg1iSMD0lHC5iOt2/ftre316oABL+rq2teXh63pr68fv0aRRy60+oCBpbcuHEjzKhrZGJ5xPPo
        0aO1Dq1Ro0ZS+VTBrVu3Bg4cqDXPwrbpkel4enrWqVNHTBI3dOhQ/U6KEXpD0tFCfn7+jh07tB4z
        ARZAcN67d8+Qwyai6/79++JPtQCE5apVq1JSUnSNTIBVtmzZIvzBOdp/9913c3NzJUwH0K+fn1/D
        hg3RuPBIq1SpoodPJ0+ejBW1yhS0a9fO399f2iSOEIako4WEhIRBgwZpjQ0GltmwYYMhZ3Z+//13
        pEsIGK5FEWDbNm3apEdkMoKCgrp16yaQFJiZmbm4uEh74iM7OxvDhMq5PjSDhEXXyrGwsBCWxIi4
        JgSpXr365s2bSTpyQtIRAmGG2srKykqMcQAW69ChgyEXnsEdnTp1EhONChA2R44c0e87CvDjtm3b
        bGxsBJICtB8QECCtdK5cuQIviDlTbm5ujv2pk3RevnzZunVrkdIBS5cuhae4lQnjQ9IRApHs6+sr
        fvoC5AWGnJhENNauXVunHocNG/bgwQM9ekQknz59GpYULkNMTEzmzJlTUFAglXTQr6enJ7vSmutD
        M9g21JvoWqR3sNiNGzdatGghfh9+8skn+hWnhH6QdIQoKir6/vvvdVIAjt440uotnXXr1lWtWlXY
        AiqgoMvLy9M1ZrB8ZGTkpEmTKleuLJzH4dVatWp99dVXqIkwLsPVg669vLxESge9X7x4USfp+Pn5
        2drait+H48ePx64Q3wVhICQdjWAKIuv+9ttvdZUO8g69Pw3p06ePwGfzfKAM9pUobn1x5OfnX7t2
        bebMmbCJmL4QwHXq1BkzZszu3bv1+ABbBax+4cKFVq1aicx0njx5opN0YOG6deuKl06vXr2CgoKw
        Dw0cFyESko5GMAX1k05wcLB+0iktLbW3txdvHCzZuXPnq1evisw+MKLi4mJUcFOmTGndurWlpSUi
        U2R3WAy5ScOGDTt27Ojs7BwWFoado3d2gIpp+PDhWs/poFMHBwcoUnwv2CSUS9WrVxcvnUaNGnl7
        e0t70ooQgKSjEb2lg3JAP+mgSmrZsiXXkAgQk6NHj0ZiJSYmsUxaWhqygBYtWlSpUkWka9SC1dEI
        zHXu3Dn9PjXLzc1du3at1vPlEAf2v07nyOGOAQMGaP12hTLYjK+//ho6JunIA0lHI4ilgoKCb775
        Rlfp6PelBIB5j0yHa0gEEMeECRMeP36sNeyRQ4WGhg4aNIj9spX4BEcTaAHqadCggZ2d3ezZszHk
        zMxM8RUKwjsiIgL1GjZGYEvYpQA6FY/p6eldu3YVc12VAizp6uoq7YVIhAAkHY0gfpDpbN++XTbp
        oMdWrVpxDYkA0TJixIh79+4JhDrCG3GItKJ+/fo4/hvoGrWYmprCZaNGjRKjPwXIX9atWyfwbY9m
        zZqxGzOLbxOgcGvbti3eBZ2ks3jx4qSkJJKOPJB0hCgpKTl8+LCu0rlw4YJ+0sGk1zXT6du3L1IY
        tWEJ3eTn52/ZsgVGQFbCEhxuTUnBZqBl6AOJSXZ2tkhHYLEbN26w23dwDZUHzycmJmJP6iQdf3//
        5s2bY12dpDNnzpyYmBiSjjyQdIRA3N68eRMe4aanNjB9sfDTp091mr4IKoC+YKuGDRtybYkA3fXp
        0yckJATrcm39CRr09vaGa1gqIT4CDeH9999/9uyZ+LEj2RG+kRhGx8orDIdbRxuQLHI6nYaMJWfO
        nPnixQuSjjyQdLSAA2D79u1F5gg4wGL6iryODoGEWV5aWop8Ki8v7/bt2yI/RVaAaOnUqdOlS5dU
        0gH07urqiqoH8SybcQA2PigoSHxugsVgzPfee0/TRuJ5SDMgIKC4uBj7Ssxexf43NzfXacgkHZkh
        6WghNzd38+bNYtJ1LDBo0KDU1FTEhnDUYYHCwsL4+Pjz5897eHg4OTk1aNDgnT9vDMY1Jw4s/+GH
        HwYHB0Nbin4RPNgSnb5LIQlwxJkzZ8R/9QyLocJChSg8cNhz0aJFGRkZGJdwy9D9wIEDxWemDHRN
        0pETko4WEMnIQWrUqKE12UFsIIRQMggHBmY2apAvvvjC2toaXkCEAESd3ikJVkQLS5YsQVLGziWh
        iwkTJvwt0jl48KD4y2oyMzPZfbyEB45XTUxMBg8eHBkZCbfyMym8RyxbDAwMbNeuHXYmt6Y40P60
        adOeP3/O9h5hbEg6WsCEjo6ORjahVTqOjo5YUuvREkfspUuXir9Hl0gQafPmzWM3G8c2uLi4/C3S
        cXNzS09P1yodbGRWVtZ3333HTvpy6wuCxZo2bbpt27bLly9HRUUpMjvoBhL38vJCRYn6FKPWY8f2
        7NlThl8TJBgkHSEwpzG5f/jhB6QSWtOQrl27hoaGlpaWcitrAIfriRMnimlQJ9Aagm337t0o3BA8
        yKT+FuksXLhQ4IbNeL64uBi6gSZWrVplZWUFlYjcD1gMYHnsOjs7u61bt8bGxmKwFy5c6N+/PyRu
        SMKIVdzd3XX9OjuhHyQd9WDyYUJDEAjjevXqiZnKmPHDhw8/deqU8Gmdhw8fjh49Wnyw6USzZs3Y
        j2F98MEH8ksHI3JycoqPj+ePHR5MSkoKCQlB/bV27dqRI0eam5tjJ3Br6gg6qlat2ty5c5HgvPfe
        e5KkjR06dPD09MR7xy/fCGkh6agBysCheOfOncOGDcPxU+TBE8tgSSyP6ik8PFytd5AHwUrt2rUz
        PEjUgjDGETs7O7tly5bYEu5ZucAeQOiyb2xzAy4DEjx9+jSSoBYtWkCF2Eggcq9qgnmH5UoGNsVA
        C02aNFmxYsXz589/oR81NiYknXJgquFAjYx90qRJOH5iQus6m7E81urbt29wcLBK7OGhmGv/DQHN
        2tvbh4WFITtDL9yzMlK5cuVbt24pDxy79OnTpw0bNmT5iJEGLgnYNmwh6j6Wq3IDIKSGpFOOjIyM
        xYsXs+tl9I4QrIXVe/XqpXJ2Iy0tbeXKlfqd6RQPep8wYULt2rWN2osA7DYR3JjLCqtdu3bpZ3D5
        wRY2b94cRx3xH/wTukLS+Qsc3Pbt24ek3fADMlY3NTU9cOAA2mRzt6ioyNfXl93Rztixh/YNH4Le
        /Pzzz8q3HC4sLBT561r/JWA7nZ2dk5OTFe8dIS0knb8oLi5mZyW52WcYb7/99pQpU9hZSfDkyZNB
        gwa9QbGnN15eXtiTinCNiYmBf9+sUdevXz8wMJCSHSNB0uHA9PLx8alZs6ZUVQn80q9fP3ZrqMzM
        zHXr1lUR96Mobzo7d+5U/BYoxu7u7i6Vx2UDipw4cWJKSgq2n00PQkJIOn+ACImKikIV8I4u92ER
        BpnORx99BOnk5eXt3bu3WbNmf2PJIydbt25VXJSMuGW/tMm99uZgYWGB5FTrpZ6EHpB0/uD169dz
        586tWrWqhFLA4f2bb74pLCw8efIk+0WUimAc8OWXXyp+hGf//v3sFDL32htFaGgofXZuDEg6fxAQ
        EIBMRNrYMDEx8fPzi4yMZD/8VkGMA5YtW5aVlQXpIMVr27btmzt2T09P5ZNThFRUdOlgSqEEGDt2
        rJmZmbSxgZpi1apVs2bNQp1VcYwDli5dym6Cs2nTJnavwjd0+BMmTGC/ukPekZaKLh3kzwgSKysr
        bqJJByKtfv361apVe0NDTm9cXV0RqzExMc2bN38Tz+YosLS0jIuLowpLciqudDCTfv31161btzZq
        1MhIJx3KjvEVyzhg27ZtKKzc3d0rV678hp7NYbz11lvXr1/Xeq8SQlcqtHSOHz+ux+1XCGHWr18f
        FRUlz2WQRgXS2bVrVzH9NI3UVFDpwDj37t0bMmSIiYkJN8UIibC1tUVhZaRfnpATbL+Tk1N+fj5J
        R1oqonRgnJiYmEmTJkl4VQ6hALv0H7NXMUOys7NJOtJSEaWTkZExb948Zpx/THgQxgDTIyIigj7A
        kpaKJR0csuLj452dnd8uu0sON7OINxN5jhk+Pj50Wy9pqVjSuXPnztChQ5HjVJBvJPyDqVq1atOm
        TS0tLY39Pk6dOrW0tJS+DyEhFUg6OFj98MMPb/pHKgSjQ4cOHh4e77//vrEz1s6dO79+/ZqSHQmp
        QNIpLCzcuHEjVVX/DAYOHBgQEDBr1ixjX/HQvXv3kpISko6EVBTpYMYkJyd//vnnxk5z0H7jxo0p
        mTIqb7/99uTJk1+9euXq6mrsi55RxOXk5JB0JKQCSSchIWH+/PnG1gEyKU9PTyT/dNrIeNSrVw9J
        a2lp6a5du6pXr27U/Yz38ebNm+iLpCMVFUg6cXFxzs7OxhYBsv2jR4+GhYU1atSISjkjgZIHIvjl
        l18uXrzYuXNno/odjR87doykIyEVSDqJiYkLFiyQIdPp169fdnY2+wV07llCOszNzZGx5uXl/fbb
        b48fPzbqr2sAvKF+fn70DSwJqUDSwTRdv369sa9CRuOYpkFBQWlpaf379zfqQbhi4uDgEBgYiDTn
        999/z8jIgIDYNRDcy1KDlrds2ULSkZCKIh2ASRMaGurk5GRra8tNKOMAy8yZMwfT9Nq1a+jLePFQ
        MenZs2dSUhKMgzcU6tmwYYOlpaXxdjLezeXLl9NN2iWkAkkHYI5GR0f/9NNPLi4uy5Ytw2TC38GD
        B0t71xs01bBhw9zcXORW69atq2g38WJMmDBhxYoVK1euXLp0aY0aNbhnpaBTp06PHj1i0gFnzpzp
        2LGj8SpZvHfbtm2jTEdCKpZ0MG8wWX/77TfYB9OotLQUR7A7d+4gNmrXri2VGtAOEv6wsDD0EhcX
        N23atApYZJ07dw57+Ndff83Pz2/VqpWEw2/atKmvr6/i+1CxsbGTJ0+G2bmXpQbv3fHjx0k6ElKx
        pMOHaejVq1dt27aVMEXHgfezzz5DyIHIyEh2DVuF8s6JEyfgXOxepHs2NjYSjh3F1OrVq9E43ji8
        g9CBq6ur8e7QiFmBZIo+vZKQii4dgMmUlpbWvn17CVN0BICtre2LFy/QOPPOlClTKlS+4+XlxQIV
        +9bc3Jx7VgqQ1EyaNKmwsFDxfShIAW+fkXYvmg0PDyfpSAhJ5w/p7Ny5s379+hJmOsDU1BRpORoH
        mLKhoaEyfFHov4cjR46wQEUWiV3BPSsR2JOoqhTSSUpK+vDDD4107gxvWXp6OklHQkg6/8nJyRky
        ZIjkH6Uz6SjOdxYVFZ07d65Lly4VJNm5cuUKUjwMPCoqSnLpdO3aNSQkBO2zdxCl1tKlS9mP0HNL
        SEfr1q3x3rFSkXVHGAhJ5z/JycndunWT3AUmJibHjh1TnO/E34KCAn9//+7du1eEfOfJkydMuEjx
        JL8nbKtWrXx9fSEC9g7in/nz55uZmRljxy5ZsoSdESfpSAVJ549vn/fu3ZubYtKB1Gnu3LkK6QD8
        g2MmogUHz392vtOmTRtUVRgvCAwMlFw6lpaWLi4uCuncv3//gw8+MNIlgrt27UJH7KQ1IQkknT9u
        J/jgwQMvL6+PP/64SpUqkugAjSDS3NzclKUD8D/ynUOHDv2DvYNxDR8+PD09vcw5/z516pTk0oFc
        Jk+eDIOzvbp27VrUVkb6fHD79u0kHWkh6fwB1FBSUpKZmdmwYUNJjpZoxNPTk/2kNwKP66YMPIR3
        li1bZozDMuPv/YU/dD1hwoSMjIwy5/z75MmTkksHjBo1Ki0tDe2jozlz5iDN4V6QmvPnz5N0pIWk
        w4Hpi4oA0pHkg3ME3qJFi9R+5MHiZOHChcaTDqrFxYsXG699YTD22bNnZ2VlYaSI1Z9++skY0kE9
        FRUVhS6ePXs2fvx4I10ciLHgzVJJVwkDIelwYFYVFxdPnTpVkgjBZEWllpiYyLWuBDp6+PDhmDFj
        jCcFePPo0aMSXnakExg7Ug+FdDZt2lSpUiXuNemAWMPDw9E+uxbBSNKZMWNGXl4epTnSQtL5C8yt
        169f16pVi5txhoFIc3V15R8k8fDs2bNt27ZFcHKLSg10w27lCa8ZrxdNmJqanjlzBgZn0lmxYoUx
        pNO5c2f2qTzKWPZrotwL0oFdd+zYsaKiIpKOtJB0yoHp1b17d0kCFY3UrVs3PT1dZcri4a5du6ys
        rJBSGckIiMC7d++i+jA3N5e/yFqzZk1mZia7iAbORZlpDOk0b97cy8sLtQ/ax540hnSQq8bGxtJl
        gZJD0ikHMp2aNWtyk84wIBQLCwsUFwg8rvUyMINTU1N9fHycnJxatWol1edlyiACg4ODS0pK5s6d
        a7xvQmrC399f8fvfGPvChQuNIZ0GDRp8//339+7dGzVqlJE+LJ8/f352djZdoSM5JJ1yIJeWSjoA
        wY8qQHHhLIMVHeCXX3559OiRMb4bgX7ZV59evnxZr149I+VTmggKClIMGdL5/PPPjSGdqlWrIqUK
        DAzs2bOnkb4A4eHhwX7InKQjLSSdcuTm5kooHdikffv2CH6udSWYetLS0saNGyd5aYB+v/rqK/QL
        tmzZ4ujoWKdOHXnUg6Tj5s2biuQOYzx37pydnR16l3YDIJrFixdfuXKld+/eRpKOs7NzTk4OxkLS
        kRaSTjkyMzOtrKy4SScFtra2BQUFXOs84DhEjuS/ZwDpoLCCcRAthYWFd+7cWbVqFZ40RmSqYGNj
        ExERAdewAWIDkNB5e3tDrFL1joIUGh06dCiyOZRXI0eOlLBxZRwcHFJSUqi8khySTjmQesgpHQTn
        7du3x4wZI+2ZHfhl1qxZkA66QMDgWA0RINnB89wSRgM6YN+6YgME2IDo6GhUWFIldEgeb9y4wc62
        XLt2DZmOkaSD3RUWFsbczQ2GkAKSzl9gbsXHx0t4b01EAiqL4uJirgMe6BGcPn3a3t5eWuksWLCA
        SYf1EhcXh9RA8jpOBQxBJdNhJCcnQ+WSnNJGFx988EFJSQm6wLgOHDjA7kliJOkgR6O7I0sOSecv
        MLdiYmIklA6CvGfPnqgvuA7UgU4TExP79OkjoREQLay84vooy+A+/fRTGT7Jqlev3v3791Wkk5GR
        0b17d0l6RyOjRo1iNw8FmzdvRg5lDOOA0aNHP3jwgPXFjYSQApLOX2BuxcbGSigdxMPEiRNVPr3i
        AzvMmzevWrVq3GoGA+ksXrxYWTr5+fk7duyQQTqNGjV6+PChinRycnJmzJghydejUIfOnj2bDQ05
        iLu7u/G+dRUeHg7joC+SjrSQdP4Cc4sVAtykMxhzc/PvvvtOq3QQoleuXGnVqhW3msFAOps2bVKW
        Dv4/efKk8eJTATIdZAcq0ikoKFi5cqUkvdepU4f9oDCaffXqFapI4w0K9qSvehoDkk45UAhIJR3k
        /Eia7ty5o/j8WBOQHcJyypQpZmZm3MqGAekcPHhQuaxD5Fy/fl0G6WDv3b17VyVQi4uLIV9JrtZB
        JnXgwAE2tLi4OKN+v/zWrVvCpTGhHySdcqAQkPCKZEtLy8uXL2uVDoB3fHx8pLqxxr/+9a9Tp06p
        BAyO2y1btjTS6Q8FMMvNmzdVpIM6CKaQRDrNmjVDysaGVlhY6ObmZjzpXL16VTlbJKSCpFMOTLIW
        LVpIEploBIf9e/fuiZEOSElJ6dSpkySnXSAdRL6KdOLj4ydNmgSpGdU7qCjZl7+5Xst4/fq1t7e3
        JNJBERoUFKQY2o4dO6pUqcK9JjUXL17EfKATOpJD0ikHomXixIlSpRv9+/dn19FzrQsCN23fvl2S
        77ij6xcvXqicS8rKyvryyy8hNaNKp0mTJvwTyQjd48ePSyIdR0dHlG+KoSE9tLW1NdKIAgIC6KMr
        Y0DSKQdm2O7du5GxGz6P0cjy5ctxTBYpHSyWlJTUvHlzw7tu2rRpenq6SoZVVFS0b98+bJVIpWIz
        GNxjEWDhdu3aRUZGqgQqHIGsQZIbFbVv3x7tK6Rz7tw54/3iFUnHSJB0yoEZhgO1qamp4ckOYszT
        0xORL37WYuFly5ZVrlzZwBCaM2dOQUGBinQQqKdOnUK6IXJos2bNGjt2rE77AZvdpUuXZ8+eqQwZ
        WxIcHCyJdNA++2oCa/nBgwfDhw9HZkfSeYMg6ZQDMwwZAcLecOnAXNevX0f+otOsjY6OrlevnoG9
        e3t7I1pUMixsRlhYWKtWrRCi3HKCnD171tfXV+TCDET+kCFDMASVIWNLwsPDJZFOjx498AYppJOZ
        mblgwQLUjIa/X3xIOkaCpFMOzDBMaMxjnYJNLTBXfHy8rlMW5dgPP/xg4MlRxW9OcY2WgYdRUVET
        J04UObSbN2/GxMTodCIG0pkxY0ZCQoJK19iYiIgISaTTs2fPkpIShXSQ0P3f//2f+PRNJ/z8/FS+
        A6HicUI/SDqqoBa4cOGC4Z8iQTo5OTm6SgfTGkdyHM8RRfqVDE2bNk1KSuL3i2dQmKB8Ezk0mAux
        rZMpsMGLFi1iv3jF9VoGHqJoNVw65ubmCxcuRPahqBwhhRUrVqBlY0jHy8uL3XSV9QVIOpJA0lEF
        k6ywsNDwqz9QyOh3lQc2AMWIfiezscrUqVNRdHBtlSc/P3/79u0ipcN+uEqn30FG5Lu4uKSmpioH
        KsBDKMxw6dSsWfObb75RPjePlk+ePNm+fXvDM1M+58+fp/LKGJB01IAD6fz58/XONRgNGjTQ+9Iy
        pBhISfQIJGzzV199lZeXxzVUHoTQwYMHxUjH2to6KysLq7Df5xK5H7Dk6tWr2c9RsR4VvHz5sn79
        +txy+lKvXj1sP3aOsnRgUrxZhmemfNgVySQdySHpqAFzGhMO89gQ6ZiZmaGm0G/KYgMQunp8KwJh
        v3fvXmRqXEM8xHwDC6MePHhwbm4ulj9y5Aj2A5rlXhMEi23evJn9+AzrTkFiYqKDg4Mh+xPA48eP
        H8chQaXM+fbbbyW/KytG/fTpU0UdR0gISUcNiJmCggJMcZHBphYoIzQ0VD/pYC3E1bRp07ABOsUS
        kiMUBSUlJVxDPE6fPq3VZegRXSODwPIxMTGVK1cWmXNha/fv3488iz/qpKSkDh06oGWdhqOCra3t
        lStXIAKV9v39/R0dHXXdV8IMGTIkISGBpGMMSDpqwJxGJYLjpyFnChCrGWU/rcs1qiNYkZ3P1kl8
        2OCQkBCBsi4sLOzdd98VDk706O7uztIlyJfdhJh7TRCs6OPjg1X4o05OTkY7BnqhefPm7HJnlfYD
        AgI6deqEsUslHbTTq1ev+Ph4ko4xIOmoB7Pt0aNH5ubm3DTUHUhHbaEhEqyI1ZFt6SQ+LBweHv6L
        5u9GP3/+nH3PQyA+8er3339fVFSE5SFf/C/ytDpWZHkWf9Tp6emjR482UDotW7ZkVyGotI9OJZfO
        2LFjX716RdIxBiQdjeTk5HzwwQd6z2MmHa4tvUDAb9u2TWSWwahUqdL9+/cFpJOZmenq6oo2haXD
        Pi3G8kgrnj59KvKb9wj7a9euqT35mp2dPX/+fAO9YG9vz/88Hly8eLFLly7SSmfDhg14+1ROHhGS
        QNLRCI7YP/30k35TGas4ODgI3B1ZDJjx0dHRdevWFb8BVatWRYKmuHaOD4ywf/9+CBFm4dbhgSGf
        OHFCcWIoLy9P5NklJIbBwcFqpYNGVq9erWu1qELr1q0hL37jqCjZ/V71eKfUgnZ2796dm5tL0jEG
        JB2NILWOjIy0trbWI04wa93d3QUyDpEgVidPniw+lmrVqoXEREA6iNjTp0/b2NgIS+fKlSvIs9gq
        paWl586dE+MLZCLsK+B8LxQUFGzatEn81035YCe0a9dOrcefPHkydOhQ4fQN4FUMjXsgCJY8fPiw
        +DsEEDpB0tEIIicjI2PmzJn6SWf69OkGZjoALXz99dfij+FNmjTh39RCGQzq0qVL7LMebh0e6C48
        PFxxNhqtxcTEiDm71Llz54cPH6qVDvImnb7jzge99+rVS6FCZdLS0j766COtjSMRGzFiBMyodRuw
        wJkzZ4qKikg6xoCkoxFEDqbd3r17RR4elYEjUMLcvn2bH346gVzp1KlT4mO1Y8eOsbGxAqc/sT3X
        rl3DYgKDwkv37t3Lycnh1im7G/GAAQO0nl0aPHjws2fP0Dt/1FAYu6WOHjuTYWJiMm7cOLXSwV5y
        cXGxtLQU2Et4CYnS48eP169fr3UbsPDly5dhfLXSwejUjpEQCUlHCBy0g4ODq1atyk1G0UA6CBLM
        b8xaQ2YnVo+IiBD/hUb+B70qveMhRtSjRw9h6aCuVD4LnpyczOoXbgkNzJgxIy4uTm2mgyfPnz9v
        iHSqVau2evVqtdJBd/7+/nCKQONIc9zc3AoLCwMDA7V+KIm9fePGDWRnmqSjdoyESEg6WkAU9evX
        T2R1owzSk4ULFxo4OzHpHzx4IF463bp1wwYrS4cdrrEZIDU19cmTJziGd+/eXSA+UaMhtcHyXBNl
        9cukSZO0Smf58uXoQuUjc2gCD7EN169fh4j1lk7t2rW9vLzUXoKE9m/dutW3b19NjWPvIblD4YnV
        b968qfUoYmFhcefOHSysVjqEgZB0tJCXl7dlyxbMZl29gxB1cnJC6BoycaGPsLAw8dJhPzvFOgWI
        /8TERDSCfxBCUMnz58+DgoKEf9vvk08+yc7OVjYXHq5YsQIa5ZbQwObNm1GUoSO+dNAayjpDpGNt
        bX316lW15+bRPl4SMCn63bRpE7YEeyY0NNTU1JR7QQO2trYoxNR+DEcYDklHC5imODa2adNGV+lA
        E0j4NaXoIkHvrCoRKR2E07Zt21BEoF/EOdIcdoEi/sdmIIrwT3h4+KBBgwSC/9ChQyqnM9Car6+v
        Vuns37+/qKhIbaBiIOyOpXpLBz5lIuBaVAI9BgQEdO7cWVPjqKeQMGIbABI9rdKxt7dHgUnSMRIk
        HS1g2uHojWRHZNgrgKRq1qzJ/+U5nUC0f/fdd+JPJDs7OyORwVqILmw5ulYJGzy8ffv2wIEDBYIf
        C8BNyiuinUePHmn9wfWjR4+qpDkKsD0XLlwwRDo2NjZ3797VTzqop5CsYRRIdvz9/bVKB7UYUkK2
        D7k+COkg6WgHkxXu6Nu3r07JDhbGAXbt2rUIYK4h3UFxN2LECK1XoAAsMGXKFNRWLMfh1ueBKEK9
        JlxePXnyhB9sMTExWu+tg3hGoHIrlAebFBgYaIh06tWrd/z4cb2lg9wNi+Gvj48PNoN7QQN4r6Oj
        o0k6RoKkIwocJzdu3Ig5rZN3kKH0799fUxyKISUlxcrKCmmO1n4XLFiAZISVRQKhgpdu3LjRrVs3
        XaWDckP49hHIRK5evarJd3jewHM61atXX7NmDTIprkUlsLXC0qlSpQrSN+wZFJ4HDhzQKh28a5As
        ScdIkHREgWD+6aefxGQcymDhJk2axMbGcq1oRq0p8OStW7cqabtLMXoZM2YMSg/UDliFW1kD6AX1
        F/umErc+D7XSQQ5lZmamafh4fvjw4bCepg3A8+jXEOlg5/fu3Rt5HNeiEthapFFdu3bV1Dj24bJl
        yyC+goICvI8knb8Xko4oMF+R2yNz0Uk6oE6dOufPn1eZu3iICc2PT5VLYHFUd3d313r6FnnQunXr
        0tPTsa7WIMECISEhvXr1Egh+bDA/O4OJatSowS3BA7tlyZIliYmJmqSDfm/evGmIdECbNm3YXX5U
        QOOXLl0SSN+wiyAs7E+Uq/v27dMqndGjR2u64IgwHJKOKBBLqEr0+AyrWrVqEAecpTJ9cch98eJF
        RkYG97gMlYjFMnCW1qtjEFF79+7V9LGRClgG+cjYsWMFgn/79u3sDAi3ThlRUVECP4WObUD5mZmZ
        qUk64P79+9gbhkindevW7H6GKmBThcsrbDbeOwwqKysLo9MqnY8//jgpKYn/rhGSQNIRBWLp6dOn
        48ePR3RxE1McpqamEyZM4B8z8VBtsqMAC9y5c0dMaoAFDh06xC6H4VbWDJaJjo6eOXOmQLPIWZAR
        qGwbsphRo0Zh+Gq9g+f37Nmj9vZdCtCCk5OTVocKAHGgC645JdCpsHRAgwYNkCUhH/Tw8NAqnUWL
        FqWkpJB0jARJRxSYfDj0ffbZZ7pKB8u3b9/+F3U/Low2BeY0Xjpy5IiYK3Ts7OxQXPALIrWg2fj4
        eHZrG259HiNGjODnLC9fvkT9IiAdX19f/uflEI3i86bs7Oz169drrRYFgHSQ0LHWlEGnR48edXR0
        FBiUtbV1Tk4OVLJy5Uqt0nFxcRFZrhJ6QNIRBSYfYmbdunV6SKdt27aIRoGkRi3o8csvv0ReoLXH
        gQMHIifCYZlbUxuvXr369NNPBeKza9euaWlpKg2ivHJwcNAknapVq548eVLt1XR4BmNHllFSUuLn
        56f1vLgAAuXVDz/80KxZM63SSU5OhlC0bsPOnTvZzXT4wyEMh6QjFkSUHt84R4gqS4dFIGtQGCw5
        Z84cMZ+XTZ8+/cWLF+KlBuksXrxYYCBdunThSwf50fvvv69JOhhjUFAQ362sEYyFfbJ27do1rRfm
        CdCqVStYg7WsDNrftGlT/fr1BQaFVzMyMkRKx9vbu7CwkIxjJEg6OnD69Om6detyE7M8iEbAPVAC
        IcrOROghnWnTpiGKtEpnxYoVcIR46SQkJAj/bjLKKL50UG4I3G+0U6dOwcHBak9dMdgJrIcPH0Ic
        WkekCXt7e00/XvrVV1/hrREYVJ06dZ48eZKamurm5iYsHbyPV65cUZu1EZJA0tGB0NDQHj16qI2Z
        Bg0aNGzYkH/CAgujKsFcFy8FBma8SOls3rxZ/GEZi6WkpCxZskQgPocMGYKkQEU6KDc8PDw0lXud
        O3cOCQnhSwe5T3FxMf7GxMRkZWUh7KEnQ6STmJjIHyme0SqdGjVqnDhxQkymg5woLCxM5DkyQg9I
        OjqAyFF7I0FEUa9evUaPHm1hYaESUXjYsmXLqKgoI0kHmjtw4ID47AlLIvhXr14tEJ9OTk5YRkU6
        7H5m6E6tdOzs7JAd8KVTUlLC/IXnQUREhKOjI0YkPChNYE/GxsaqdAHwzNq1a2vVqiUwKHNzc1dX
        V5SWWqUzZswYdisyrnVCakg6OpCdnf3ll1/yRYCHkA4cYWlpyX+pWbNmd+/e1UM606dP1yodNH72
        7FmdGs/Pz2c5C9cEj3nz5uXk5Ki0CX34+PggXNVKx8rK6syZM3zpqIAd6O7urnVQmmjRokVkZCS6
        UOkFD5cvX16tWjW128bAlg8bNgzVmbB0sGFYAG4i6RgPko4OoFLYunUr/+QuHvbu3XvRokU1a9bk
        v9S4cWP2u5RcK+JAIDk7OwvHJ14aPHhweHi4ShAKg5xl48aNAtL57LPP+D+EgO2/cOGCJungST8/
        P63nQbCAr6+vmZmZgB0EgHSeP3+OLlR6wUOt0gEQdFxc3LJly4Sls2fPHr5zCQkh6egAAm/37t0o
        Mfhm6d69+4wZM2rUqMF/ycbG5vTp03pIh33GpNKgMngJ5V50dLRKEGqCLVZaWir8c1pqLw7EusHB
        wZouVhQpHbwaGhqKKkltI1rR9GN7eChGOrD/vXv3kD8KSAe5akBAANI6ko7xIOnoAMRx+PDh2rVr
        881ia2vbvn37ypUr81+ytrY+cuQIk45KtAiAJdeuXSssHcTYihUr0tPTRTbLFkM4QZ0C0kG//F9f
        wbrwhYWFhd7SYQ3GxMSgDhXoXQCBT6/ESAdvxKFDhzp06CBwgeKAAQMiIiIwEJKO8SDp6AAmYkhI
        yHvvvcc3izLcs2XgYf369T09PSEdxAY/YDSBJX/88UcEp0Ag4aX169cLf/lALdgegfsE79q1S+Wr
        pwBdINNBIqCfdPA8+zwIinRzcxMIewEgnYSEBH4XeEaMdGDM4cOHW1lZCeRZyPLoW1fGhqSjA5iI
        mPRz585VMYsAytLhWhEH+kJRpunTIgZe2rRpk8iveipz/vz51q1baxrF/v37UV+otIle2E0h1EYs
        WmM3MBbYEvZScXEx+xSMW1MXFCeSWYMK8IwY6QAMWTh5ZN8gg3AFBkIYCElHBzAREY0eHh5aJ7cC
        Q6SDPN9I0rl9+7bA5cXe3t586bArkjVlXl988QX7xEfrliCez507V6dOHW5NXWjcuPGNGzf4RsDD
        lStXCv/uFQPjZXCPy9O8efPAwECtZ6YIAyHpcEdgkWBhHAy1/oaJAsxvvaWTkZFhY2MjUAsgxr7+
        +ms9pPP06dOJEydqOub7+voqvrPONhv/37lzB6PW5KnvvvuOfzcMTUB53bp10xT5AmBvIEdTKx12
        nY5W6Qgze/bsqKgouizQ2JB0dJMOQCJgbW0tMmYMkQ7CeMaMGcLScSn7PrSuQ0CR6OzsjLRFWDoI
        b4DlEYfsDsdql0fa4ufnp/UiHQaWiY6OnjJlinCZoxbs9uPHj/PzKTzcsGFD3bp1DZEOksodO3bk
        5ubq+k4RukLS0ZkLFy506NDB2NIBpaWl+/fvF/igBzE2bty4hw8fiol2ZZBDoSDSKh1GTk5OZmam
        l5eXpk+a27dvDyWJHCAazMrKcnNzEz5HrpZ69eodOnRIrXS0fuFTKw0aNPD392dfTOXa/fMTN0Ja
        SDo6ExkZKf5uXgZK59tvvxWQDhqvXbv2sWPHlINQTJwgh2I3QlUrnTNnzpSUlPxSdh8ctJyWllZY
        WIgn1UoHLQwdOhTFl3C/aIc1CJAT/fjjj8Knq9QC6cB92JMqfaHx7du3C5eiWunXr19YWBg2UtE4
        OlJsM7t5GDlIEkg6OpOYmIjiX+T8ZtI5ePCgHtK5ffu2vb29gHQA2vfw8EBRgMBDSAAx50GxzMaN
        GzWFfXh4OKwE77Al4b6ioqJ9+/ZheW4JJbABkydPfvLkiXBAYpMU50rw/8mTJxs2bKirI1gyolY6
        e/bsadq0qSHSmTRpEg4nykUi/lF0xOyjeIkwBJKOzqSmpgrfeU8ZxGSjRo0uXryoq3QQ546OjmLS
        ARzhfXx8sDwCBkEiJjCwMUgNLCws+I2bmJgg9hSBjb/4H+WVs7OzJukMGDAAOQJbUqB35WBGZiT8
        K6Nqsba29vPz4/eChwcOHLCzszNEOnhP4+PjhYdASAJJRyyYiyykX7169cknnwgnIAqqVq26du3a
        nJwczGauIRGgFxRNiH9IAVHNtfUneEb5SUQavINyKTk5GVsIuFY0g2XOnj3bvn17vnS6dOmi8k1u
        bDkqrA8//FCTdMzNzZEHoQARk2QxXr58yW5RxrUiDisrKyRozK1cQ2WgU19f3zZt2hginZUrV2Zk
        ZKBlkUMg9IakIwrUGikpKSg08H9CQsKsWbNEBgzCoGvXrrreTwcLs8xCWS6M5s2bT5gwAaUE97gs
        7OEOS0vLJk2aeHt7ozJip4EFNIdXkbzw7x+IplBlwKrKgYf/09PTP/74Y7XSAVhr7NixKhWW8HjR
        xaeffqqrdGBhbB7UptI4tvDnn3/u2LGjIdLR7+IDQg9IOqLAXMREZyAJnzlzpsiAgQ5atmz5/Plz
        rMi1JQIsjERAbZCjtV27di1ZskTFR+gIm8RuMfHixQt4h52U0QS6YN/t4tYvA20uXboUB3xF7MFc
        AM/As5qkA0xNTVGexMXFiQladH3+/HkkJrpKB/To0SM7O1vFp+gUDQr/GoRWduzYwQ4qhLEh6ahB
        ZU6rEBMTM3XqVJHzG2Hs6Oio8kGsVrBwQECA2iCHVlBJHThwwNramnuqDHQEEMZHjhxhR2yt8b9u
        3TqVUcBcixYtQjGlWJeZC3/9/PwEpIOuK1WqBFGqvbMfA89jXKjCdu7ciaoTy/OLO61AVbdu3VKc
        k2agZeEf29OKg4PD6dOn2dliwtiQdNSAGBPwzuPHj8eNGydyfteuXRv64FcEwiCKsAH29vYIZq6h
        P0GgIrZv3749fPhwftBCOjdv3hR5xOZLB92xO12piANBDm8GBQX169cPXfC3CjDlId24e/euppM7
        OTk5GzdurFy5MoyDrtW2I0zjxo19fHz40oGJ+vbtq7d0xowZc+/ePZVmCSNB0tENzMsTJ07geCvy
        KN20adPCwkIYB4EBxKsHS6JQ4kc4+h05ciQixMXFxcLCwsTEBAEM8A+CedSoUcg1xAQPJLJq1Sq+
        dFq0aIFUDpvKLfcneAYeTElJWbNmDVIeTd5Bg9iYo0ePItvi1vwTmOjs2bNmZmYYFEah0gKeNDc3
        13p/LyYdfkqCinLo0KFohFtOF7Al06ZNe/r0KUlHHkg6OoAMCEk4DuZ8F6gF4TdlyhRNh31hsEpe
        Xh6cpRKE6NfOzu7gwYOxsbHe3t6urq6wD9iwYQMKKyQpSHPEqA1Jx+eff86XDnj06JHaDWbeuXPn
        DrIh1EdYkltNCTzJvOPl5YXdpdwOhIUcjf+RHB6iNeQa169fR+XVsGFDtS0zWrZsefnyZb50MjIy
        xo8fr590gKmpqYeHR3Z2th7vFKErJB0duHjxIkoeTcd5Pkg93N3d9Tt+YvYXFxcvXbqU7wVEKY7M
        ycnJUADCD5YB+AfgGawoJnKeP3/+0UcfqTTOQIaFprjlyoOW0QW6dnNza9CgARITbh0lsIUAeyk4
        OBgLc2uW/ZY5dojyiSEshuymdevWW7duffXqFTtz1KxZM03JDpbv3r07xIrNUxErOpo/fz7a5xbV
        EbRcv379Q4cOYZ+L2XuEIZB0xILA/vHHH3EM1xQSfKpUqYLjp95JO3rcsWMH/+iNCLG1td29ezdK
        GAQbA0EIWMD8YR3NkcNeDQ8PRz2iVjrff/+9QOzheXSHLAwZx4wZM+AIDBObxK38J2gZtZ6yvFC/
        ODo62tjYwFaokqDvjh07Itt6+PAhusNgsaOQu/GTOwUw1MKFCzWdccP2qL3ySCQYQteuXX/++Wf6
        4NzYkHTEwr6mqDZK1WJhYfHuu+9u3rxZb+lgxRMnTqj9zAibMWDAAKQSKgd8BhMQ96A8TBlAQDoY
        pta7EbJ2EJ9Xr16dPn06bNKoUaPatWujemKNYPiTJk16/fo1t0LZF77u3r2LwhAJxdmzZyMiIrBL
        YRAME1uLBvF3//798JEmcaCLCxcu8NMcBgrGsWPHYgP4BhQJ+u3du/epU6egVPKO8SDpiCUtLW35
        8uWKeIALatWqhYM8e8gHh3FIAaGlHCGYyuJnM1bE6jj88qMIzyADwvYg0rildQHbEBsbq+m+GcjO
        tEoHYAF4BwqAemATLy+vr7/+eurUqXDZkCFDFixY8OzZM+VMR7E8TPRHQVhWEiqMwxYICgoaPHgw
        qiT+kLHnO3TokJqaikbUbhva2bhxI6okQ5IdrGtnZ8fKPXTENU1ICklHFJjliEMfHx+EBFKMgQMH
        TpgwYdWqVZ06deImbHkwfZHmsMtzlCME/ys7SBgsjLCEuZo0acIPQoDYRrSrjUCtIOb37NmDSodr
        SwnoQ6dTG2xQTChoFqNG/oK/TCjcQiJAO2jk2rVrSHb44zUzM3NyclI5Oa0Mnoeju3Tpord0GOga
        QndxcUEiJn4n8MHwDVn9HwxJRyyYQJjxKSkpyBHi4+ORYuBIjrDnpmp5MO/nzZuHIBQ57TQthucz
        MzO/+OILtYHUvXt3hKhOga0ALSclJaGSUvm0CCVSaGiorgGDhbEZANbAugD/4KFOjQAsD1u1a9cO
        KZiKd6ysrHbu3IlXuUV5sHVdXV2Rgap1tHiwt+Gdw4cPo0Fdh6BAwI8VHJKObmAaMRBXP/74o/J3
        oBQgfZg2bVpMTAykw62mDTTI/ccDc/fEiRM1atTgWleif//+YWFhelcBkEJCQsK2bdtGjhyJBAGp
        WZ8+faAh5SuS5QdJFraE/xGhjY3NgwcPtO7S9PR0VHaaPtGvVKmSg4PDpEmTpk+fPnbs2L59+yJX
        tbe3r1atGreEEr169UKyg73ENU1IBElHZ8qc82/UEQsXLsQk5mZo2U/09+zZc+bMmbt3787IyEB4
        6K0DZdBXamqqu7v70KFD7ezsFGeRcCieO3cuci69owItY92ioiKkbJcuXTp79mxISEh2drb4BM0Y
        YMeqSAd5h6Oj49q1a+EjuJ5bTgMYUVRU1IoVK6ytrfnpIcyF/CUxMRHDfPnyJZQdEBDg5+fn4eEx
        efJkZFiKT+IsLCxmz56NfBYN/o174x9JBZIO5qv41EMrEIq/v/+sWbPGjx8/derUTz/9dOvWrQhd
        1CzIySXRjQJM+vz8/Dt37iBg1q9fv3z58mXLlq1Zswa1FULUwJDA6gChpXdNJC3YAJSTSD1Y8Pfr
        1++zzz47duxYXl4ethCvcstpBtuPDGXXrl0q38YyMTH58MMPsSfZTgNoDUNGs9AZMtOTJ0/CPugd
        7+aGDRueP3/O3kosyTVNSEEFkg6bXtwDg8F8xUxFohEZGYn5yj79xWxmoSvtNEVrbOMhTfRSUAYy
        FDyUxBFoAbCmAPfs3wQ2IDo6evv27Sj0vvnmmxs3bqBiQvAz44jcPCyJHYVjwKpVq8aMGTNs2LAR
        I0ZAXkFBQXiPsDOxTNlY/wAL4xmA/Yn3NDc3F+8m/mFLYgHWJiEVFb28YtOOe6A7WBdTFhjSCKEC
        diYLfrjGkMjH+5KZmfngwYPbt28jT4yLi0Nr9Gb97ZB0DJp/WJ3BPSakAPsTaihLPgwq9xTtIEti
        4H96s/526EQyQRCyQtIhCEJWSDoEQcjKP0E6qNu5/3gov4Rinup5gvjb+SdnOlAM+1AZFJf9RgL3
        AkEQfx8VpbyiNIcg/kv4B0qn7JNWuikBQfyXQieSCYKQFZIOQRCyQtIhCEJWSDoEQcgKSYcgCFkh
        6RAEISskHYIgZIWkQxCErJB0CIKQFZIOQRCyQtIhCEJWSDoEQcgKSYcgCFkh6RAEISskHYIgZIWk
        QxCErJB0CIKQFZIOQRCyQtIhCEJWSDoEQcgKSYcgCFkh6RAEISskHYIgZIWkQxCErJB0CIKQFZIO
        QRCyQtIhCEJWSDoEQcgKSYcgCFkh6RAEISskHYIgZIWkQxCErJB0CIKQFZIOQRCyQtIhCEJWSDoE
        QcjIf/7z/1wWfYoQvBlfAAAAAElFTkSuQmCC
    </Bmp>
    <BkgAlpha>255</BkgAlpha>
    <Text></Text>
    <ImageRepresentation>
      <Presentation>MODE_VALUE_AS_IMAGE</Presentation>
      <FallBack>0</FallBack>
      <CellImageStyle></CellImageStyle>
    </ImageRepresentation>
    <AllowVerticalScrollBar>false</AllowVerticalScrollBar>
    <AllowHorizontalScrollBar>false</AllowHorizontalScrollBar>
    <ActionItems></ActionItems>
  </Layout>
  <PrintSettings></PrintSettings>
  <UserSized>true</UserSized>
</TextObjectProperties>
